{
	"pages": [ //pages数组中第一项表示应用启动页，参考：https://uniapp.dcloud.io/collocation/pages
		{
			"path" : "pages/loading/loadingindex",
			"style" : 
			{
				"navigationBarTitleText" : "",
				"navigationBarBackgroundColor": "#8cd98f",
				"navigationStyle": "custom"
			}
		},
		{
			"path": "pages/loading/loading1",
			"style": {
				"navigationBarTitleText" : ""

			}
		},
		{
			"path" : "pages/loading/loading2",
			"style" : 
			{
				"navigationBarTitleText" : ""
			}
		},
		{
			"path" : "pages/loading/loading3",
			"style" : 
			{
				"navigationBarTitleText" : "",
				"navigationStyle": "custom"
				
			}
		},
		{
			"path" : "pages/loading/check1",
			"style" : 
			{
				"navigationBarTitleText" : ""
			}
		},
		{
			"path" : "pages/loading/check2",
			"style" : 
			{
				"navigationBarTitleText" : ""
			}
		},
		{
			"path": "pages/loginANDregister/register",
			"style": {
				"navigationBarTitleText": "register",
				"navigationStyle": "custom"
			}
		},
		{
			"path": "pages/loginANDregister/login",
			"style": {
				"navigationBarTitleText": "login",
				"navigationStyle": "custom"
			}
		},
		{
			"path": "pages/index/index",
			"style": {
				"navigationBarTitleText": "首页",
				"navigationStyle": "custom"
			}
		},
		{
			"path": "pages/index/searchpage/searchpage",
			"style": {
				"navigationBarTitleText": "搜索页",
				"navigationStyle": "custom"
			}
		},
		{
			"path": "pages/index/expertpage/expertpage",
			"style": {
				"navigationBarTitleText": "食谱专家",
				"navigationStyle": "custom"
			}
		},
		{
			"path": "pages/index/ownpage/ownpage",
			"style": {
				"navigationBarTitleText": "个人",
				"navigationStyle": "custom"
			}
		},
		{
			"path" : "pages/individual/video/video",
			"style" : 
			{
				"navigationBarTitleText" : ""
			}
		},
		{
			"path" : "pages/individual/totalCount/totalCount",
			"style" : 
			{
				"navigationBarTitleText" : ""
			}
		},
		{
			"path" : "pages/individual/selectfood/selectfood",
			"style" : 
			{
				"navigationBarTitleText" : ""
			}
		},
		{
			"path" : "pages/individual/privateMenu/privateMenu",
			"style" : 
			{
				"navigationBarTitleText" : ""
			}
		},
		{
			"path" : "pages/individual/creatMenu/creatMenu",
			"style" : 
			{
				"navigationBarTitleText" : ""
			}
		},
		{
			"path" : "pages/expertpage-individual/expert-page/expert-page",
			"style" : 
			{
				"navigationBarTitleText" : ""
			}
		},
		{
			"path" : "pages/ownpage-individual/my-smart-kitchen/my-smart-kitchen",
			"style" : 
			{
				"navigationBarTitleText" : ""
			}
		}
	],
	"globalStyle": {
		"navigationBarTextStyle": "black",
		"navigationBarTitleText": "uni-app x",
		"navigationBarBackgroundColor": "#F8F8F8",
		"backgroundColor": "#F8F8F8"
	},
	"tabBar": {
		// "selectedColor": "#2b9939",
		// "height": "190rpx",
		"iconWidth":"190rpx",
		"borderStyle":"1px solid rgb(255,255,255)",
		"backgroundColor": "#fff",
		"list": [
			{
				"pagePath": "pages/index/index",
				"iconPath": "/static/flavormate静态文件/组件/33.png",
				"selectedIconPath": "/static/flavormate静态文件/组件变绿/37.png"
			},
			{
				"pagePath": "pages/index/searchpage/searchpage",
				"iconPath": "/static/flavormate静态文件/组件/34.png",
				"selectedIconPath": "/static/flavormate静态文件/组件变绿/38.png"
			},
			{
				"pagePath": "pages/index/expertpage/expertpage",
				"iconPath": "/static/flavormate静态文件/组件/35.png",
				"selectedIconPath": "/static/flavormate静态文件/组件变绿/39.png"
			},
			{
				"pagePath": "pages/index/ownpage/ownpage",
				"iconPath": "/static/flavormate静态文件/组件/36.png",
				"selectedIconPath": "/static/flavormate静态文件/组件变绿/40.png"
			}
		]
	},
	"uniIdRouter": {}
}
